chatwoot_client/__init__.py
chatwoot_client/__main__.py
chatwoot_client/action.py
chatwoot_client/definitions/actions.py
chatwoot_client/definitions/schemas/input_schemas.py
chatwoot_client/definitions/schemas/webhooks_events.py
chatwoot_client/http.py
chatwoot_client-0.1.2.dist-info/LICENSE
chatwoot_client-0.1.2.dist-info/METADATA
chatwoot_client-0.1.2.dist-info/WHEEL
chatwoot_client-0.1.2.dist-info/RECORD
