Metadata-Version: 2.1
Name: chatwoot-client
Version: 0.1.2
Summary: 
Author: Junior Vidotti
Author-email: jrvidotti@gmail.com
Requires-Python: >=3.11,<4.0
Classifier: Programming Language :: Python :: 3
Classifier: Programming Language :: Python :: 3.11
Classifier: Programming Language :: Python :: 3.12
Requires-Dist: httpx (>=0.25,<0.26)
Requires-Dist: pydantic (>=2.6.1,<3.0.0)
